archery/__init__.py
archery/api.py
pyArchery-1.2.0.dist-info/LICENSE
pyArchery-1.2.0.dist-info/METADATA
pyArchery-1.2.0.dist-info/WHEEL
pyArchery-1.2.0.dist-info/top_level.txt
pyArchery-1.2.0.dist-info/zip-safe
pyArchery-1.2.0.dist-info/RECORD
