Metadata-Version: 2.1
Name: pyArchery
Version: 1.2.0
Summary: Python library enumerating the Archery Tool RESTFul API endpoints.
Home-page: https://github.com/archerysec/
Author: Anand Tiwari
Author-email: anandtiwarics@gmail.com
License: MIT License
Keywords: pyArchery,api,security,software,ArcherySec
Platform: UNKNOWN
Classifier: Intended Audience :: Developers
Classifier: Natural Language :: English
Classifier: License :: OSI Approved :: MIT License
Classifier: Topic :: Software Development
Classifier: Topic :: Software Development :: Libraries :: Python Modules
Classifier: Programming Language :: Python
Requires-Dist: requests
